randomheader/__init__.py
randomheader/header.py
randomheader/agents/accepts.txt
randomheader/agents/encodings.txt
randomheader/agents/referrer.txt
randomheader/agents/user-agents.txt
randomheader-0.4.dist-info/LICENSE
randomheader-0.4.dist-info/WHEEL
randomheader-0.4.dist-info/METADATA
randomheader-0.4.dist-info/RECORD
