Metadata-Version: 2.1
Name: randomheader
Version: 0.4
Summary: Generates random HTTP headers for requests
Author: elgransenor
Requires-Python: >=3.5
Classifier: License :: OSI Approved :: MIT License
Project-URL: Home, https://github.com/joenano/randomheader
